llama_index/readers/nougat_ocr/__init__.py
llama_index/readers/nougat_ocr/base.py
llama_index_readers_nougat_ocr-0.4.1.dist-info/METADATA
llama_index_readers_nougat_ocr-0.4.1.dist-info/WHEEL
llama_index_readers_nougat_ocr-0.4.1.dist-info/licenses/LICENSE
llama_index_readers_nougat_ocr-0.4.1.dist-info/RECORD
