Metadata-Version: 2.4
Name: llama-index-readers-nougat-ocr
Version: 0.4.1
Summary: llama-index readers nougat_ocr integration
Author-email: Your Name <you@example.com>
Maintainer: mdarshad1000
License-Expression: GPL-2.0-or-later
License-File: LICENSE
Keywords: academic papers,ocr,pdf
Requires-Python: <4.0,>=3.9
Requires-Dist: llama-index-core<0.15,>=0.13.0
Requires-Dist: nougat-ocr<0.2,>=0.1.17
